de_workflow/__init__.py
de_workflow/main.py
de_workflow/report.py
de_workflow/utils.py
de_workflow-0.2.2.dist-info/entry_points.txt
de_workflow-0.2.2.dist-info/LICENSE
de_workflow-0.2.2.dist-info/WHEEL
de_workflow-0.2.2.dist-info/METADATA
de_workflow-0.2.2.dist-info/RECORD
