Metadata-Version: 2.1
Name: de-workflow
Version: 0.2.2
Summary: 
Author: Nick Anthony
Author-email: nanthony007@gmail.com
Requires-Python: >=3.10,<3.11.0
Classifier: Programming Language :: Python :: 3
Classifier: Programming Language :: Python :: 3.10
Requires-Dist: click (>=8.1.3,<9.0.0)
Requires-Dist: datapane (>=0.14.0,<0.15.0)
Requires-Dist: pandas (>=1.4.2,<2.0.0)
Requires-Dist: plotly (>=5.7.0,<6.0.0)
Requires-Dist: requests (>=2.27.1,<3.0.0)
Requires-Dist: rich (>=12.3.0,<13.0.0)
